i3pystatus/__init__.py
i3pystatus/abc_radio.py
i3pystatus/alsa.py
i3pystatus/anybar.py
i3pystatus/backlight.py
i3pystatus/battery.py
i3pystatus/bitcoin.py
i3pystatus/clock.py
i3pystatus/cmus.py
i3pystatus/cpu_freq.py
i3pystatus/cpu_usage.py
i3pystatus/cpu_usage_bar.py
i3pystatus/cpu_usage_graph.py
i3pystatus/disk.py
i3pystatus/dota2wins.py
i3pystatus/dpms.py
i3pystatus/file.py
i3pystatus/github.py
i3pystatus/google_calendar.py
i3pystatus/gpu_mem.py
i3pystatus/gpu_temp.py
i3pystatus/iinet.py
i3pystatus/keyboard_locks.py
i3pystatus/lastfm.py
i3pystatus/load.py
i3pystatus/makewatch.py
i3pystatus/mem.py
i3pystatus/mem_bar.py
i3pystatus/modsde.py
i3pystatus/moon.py
i3pystatus/mpd.py
i3pystatus/net_speed.py
i3pystatus/network.py
i3pystatus/now_playing.py
i3pystatus/online.py
i3pystatus/openfiles.py
i3pystatus/openstack_vms.py
i3pystatus/openvpn.py
i3pystatus/parcel.py
i3pystatus/pianobar.py
i3pystatus/ping.py
i3pystatus/plexstatus.py
i3pystatus/pomodoro.py
i3pystatus/pyload.py
i3pystatus/reddit.py
i3pystatus/regex.py
i3pystatus/runwatch.py
i3pystatus/scratchpad.py
i3pystatus/sge.py
i3pystatus/shell.py
i3pystatus/solaar.py
i3pystatus/spotify.py
i3pystatus/syncthing.py
i3pystatus/taskwarrior.py
i3pystatus/temp.py
i3pystatus/text.py
i3pystatus/timer.py
i3pystatus/uname.py
i3pystatus/uptime.py
i3pystatus/vk.py
i3pystatus/weekcal.py
i3pystatus/whosonlocation.py
i3pystatus/window_title.py
i3pystatus/xkblayout.py
i3pystatus/zabbix.py
i3pystatus/core/__init__.py
i3pystatus/core/color.py
i3pystatus/core/command.py
i3pystatus/core/desktop.py
i3pystatus/core/exceptions.py
i3pystatus/core/imputil.py
i3pystatus/core/io.py
i3pystatus/core/modules.py
i3pystatus/core/settings.py
i3pystatus/core/threading.py
i3pystatus/core/util.py
i3pystatus/mail/__init__.py
i3pystatus/mail/imap.py
i3pystatus/mail/maildir.py
i3pystatus/mail/mbox.py
i3pystatus/mail/notmuchmail.py
i3pystatus/mail/thunderbird.py
i3pystatus-3.35.dist-info/DESCRIPTION.rst
i3pystatus-3.35.dist-info/METADATA
i3pystatus-3.35.dist-info/RECORD
i3pystatus-3.35.dist-info/WHEEL
i3pystatus-3.35.dist-info/entry_points.txt
i3pystatus-3.35.dist-info/metadata.json
i3pystatus-3.35.dist-info/top_level.txt
i3pystatus-3.35.dist-info/zip-safe
